README.md
setup.py
editor/__init__.py
spritex.egg-info/PKG-INFO
spritex.egg-info/SOURCES.txt
spritex.egg-info/dependency_links.txt
spritex.egg-info/entry_points.txt
spritex.egg-info/not-zip-safe
spritex.egg-info/requires.txt
spritex.egg-info/top_level.txt