Metadata-Version: 1.1
Name: spritex
Version: 0.1.3
Summary: A simple tool for extracting sprites from full frames. Useful for AI projects. 
Home-page: https://github.com/codetorex/spritex
Author: codetorex
Author-email: 627572616b@gmail.com
License: MIT License
Keywords: spritex,sprite,extractor,unique color
Platform: UNKNOWN
Classifier: Development Status :: 4 - Beta
Classifier: Topic :: Multimedia :: Graphics :: Editors :: Raster-Based
Classifier: Intended Audience :: Developers
Classifier: Natural Language :: English
Classifier: License :: OSI Approved :: MIT License
Classifier: Operating System :: OS Independent
Classifier: Programming Language :: Python
Classifier: Programming Language :: Python :: 3.5
Classifier: Programming Language :: Python :: 3.6
